{
  "generated_at": "2026-01-28T10:01:52.967453",
  "data_sources": {
    "singularity": "https://singularityresearchfund.com/opendoor-tracker",
    "parcl": "Parcl Research CSV exports",
    "note": "Unified dataset combining both sources"
  },
  "as_of": "2026-01-27",
  "velocity": {
    "q1_sales": 744,
    "q1_revenue": 288469700.0,
    "daily_avg_sales": 22.2,
    "daily_avg_revenue": 8581481.481481481,
    "avg_home_price": 387728,
    "best_day": "2026-01-27",
    "best_day_sales": 43
  },
  "pnl": {
    "win_rate": 79.1,
    "avg_profit": 46407,
    "avg_loss": -30374,
    "total_realized": 8401357.0,
    "wins": 219,
    "losses": 58,
    "coverage_pct": 37.2
  },
  "revenue_chart": [
    {
      "date": "Jan 01",
      "date_full": "2026-01-01",
      "revenue": 3840000.0,
      "revenue_millions": 3.84,
      "sales_count": 9
    },
    {
      "date": "Jan 02",
      "date_full": "2026-01-02",
      "revenue": 1330000.0,
      "revenue_millions": 1.33,
      "sales_count": 5
    },
    {
      "date": "Jan 03",
      "date_full": "2026-01-03",
      "revenue": 4940000.0,
      "revenue_millions": 4.94,
      "sales_count": 14
    },
    {
      "date": "Jan 04",
      "date_full": "2026-01-04",
      "revenue": 10220000.0,
      "revenue_millions": 10.22,
      "sales_count": 27
    },
    {
      "date": "Jan 05",
      "date_full": "2026-01-05",
      "revenue": 9070000.0,
      "revenue_millions": 9.07,
      "sales_count": 25
    },
    {
      "date": "Jan 06",
      "date_full": "2026-01-06",
      "revenue": 6390000.0,
      "revenue_millions": 6.39,
      "sales_count": 18
    },
    {
      "date": "Jan 07",
      "date_full": "2026-01-07",
      "revenue": 9090000.0,
      "revenue_millions": 9.09,
      "sales_count": 20
    },
    {
      "date": "Jan 08",
      "date_full": "2026-01-08",
      "revenue": 8310000.000000001,
      "revenue_millions": 8.31,
      "sales_count": 20
    },
    {
      "date": "Jan 09",
      "date_full": "2026-01-09",
      "revenue": 9750000.0,
      "revenue_millions": 9.75,
      "sales_count": 26
    },
    {
      "date": "Jan 10",
      "date_full": "2026-01-10",
      "revenue": 3730000.0,
      "revenue_millions": 3.73,
      "sales_count": 11
    },
    {
      "date": "Jan 11",
      "date_full": "2026-01-11",
      "revenue": 2860000.0,
      "revenue_millions": 2.86,
      "sales_count": 9
    },
    {
      "date": "Jan 12",
      "date_full": "2026-01-12",
      "revenue": 10840000.0,
      "revenue_millions": 10.84,
      "sales_count": 25
    },
    {
      "date": "Jan 13",
      "date_full": "2026-01-13",
      "revenue": 9840000.0,
      "revenue_millions": 9.84,
      "sales_count": 26
    },
    {
      "date": "Jan 14",
      "date_full": "2026-01-14",
      "revenue": 12320000.0,
      "revenue_millions": 12.32,
      "sales_count": 33
    },
    {
      "date": "Jan 15",
      "date_full": "2026-01-15",
      "revenue": 8369999.999999999,
      "revenue_millions": 8.37,
      "sales_count": 20
    },
    {
      "date": "Jan 16",
      "date_full": "2026-01-16",
      "revenue": 9430000.0,
      "revenue_millions": 9.43,
      "sales_count": 25
    },
    {
      "date": "Jan 17",
      "date_full": "2026-01-17",
      "revenue": 3180000.0,
      "revenue_millions": 3.18,
      "sales_count": 9
    },
    {
      "date": "Jan 18",
      "date_full": "2026-01-18",
      "revenue": 4780000.0,
      "revenue_millions": 4.78,
      "sales_count": 13
    },
    {
      "date": "Jan 19",
      "date_full": "2026-01-19",
      "revenue": 8530000.0,
      "revenue_millions": 8.53,
      "sales_count": 24
    },
    {
      "date": "Jan 20",
      "date_full": "2026-01-20",
      "revenue": 14270000.0,
      "revenue_millions": 14.27,
      "sales_count": 41
    },
    {
      "date": "Jan 21",
      "date_full": "2026-01-21",
      "revenue": 12700000.0,
      "revenue_millions": 12.7,
      "sales_count": 31
    },
    {
      "date": "Jan 22",
      "date_full": "2026-01-22",
      "revenue": 15510000.0,
      "revenue_millions": 15.51,
      "sales_count": 39
    },
    {
      "date": "Jan 23",
      "date_full": "2026-01-23",
      "revenue": 12080000.0,
      "revenue_millions": 12.08,
      "sales_count": 30
    },
    {
      "date": "Jan 24",
      "date_full": "2026-01-24",
      "revenue": 2780000.0,
      "revenue_millions": 2.78,
      "sales_count": 9
    },
    {
      "date": "Jan 25",
      "date_full": "2026-01-25",
      "revenue": 5460000.0,
      "revenue_millions": 5.46,
      "sales_count": 16
    },
    {
      "date": "Jan 26",
      "date_full": "2026-01-26",
      "revenue": 12290000.0,
      "revenue_millions": 12.29,
      "sales_count": 32
    },
    {
      "date": "Jan 27",
      "date_full": "2026-01-27",
      "revenue": 19790000.0,
      "revenue_millions": 19.79,
      "sales_count": 43
    }
  ],
  "sales_chart": [
    {
      "date": "Jan 01",
      "date_full": "2026-01-01",
      "count": 9,
      "moving_avg": 14.9
    },
    {
      "date": "Jan 02",
      "date_full": "2026-01-02",
      "count": 5,
      "moving_avg": 14.6
    },
    {
      "date": "Jan 03",
      "date_full": "2026-01-03",
      "count": 14,
      "moving_avg": 14.4
    },
    {
      "date": "Jan 04",
      "date_full": "2026-01-04",
      "count": 27,
      "moving_avg": 15.0
    },
    {
      "date": "Jan 05",
      "date_full": "2026-01-05",
      "count": 25,
      "moving_avg": 15.7
    },
    {
      "date": "Jan 06",
      "date_full": "2026-01-06",
      "count": 18,
      "moving_avg": 15.7
    },
    {
      "date": "Jan 07",
      "date_full": "2026-01-07",
      "count": 20,
      "moving_avg": 15.8
    },
    {
      "date": "Jan 08",
      "date_full": "2026-01-08",
      "count": 20,
      "moving_avg": 15.8
    },
    {
      "date": "Jan 09",
      "date_full": "2026-01-09",
      "count": 26,
      "moving_avg": 15.7
    },
    {
      "date": "Jan 10",
      "date_full": "2026-01-10",
      "count": 11,
      "moving_avg": 15.4
    },
    {
      "date": "Jan 11",
      "date_full": "2026-01-11",
      "count": 9,
      "moving_avg": 14.8
    },
    {
      "date": "Jan 12",
      "date_full": "2026-01-12",
      "count": 25,
      "moving_avg": 15.4
    },
    {
      "date": "Jan 13",
      "date_full": "2026-01-13",
      "count": 26,
      "moving_avg": 16.1
    },
    {
      "date": "Jan 14",
      "date_full": "2026-01-14",
      "count": 33,
      "moving_avg": 16.4
    },
    {
      "date": "Jan 15",
      "date_full": "2026-01-15",
      "count": 20,
      "moving_avg": 16.4
    },
    {
      "date": "Jan 16",
      "date_full": "2026-01-16",
      "count": 25,
      "moving_avg": 16.3
    },
    {
      "date": "Jan 17",
      "date_full": "2026-01-17",
      "count": 9,
      "moving_avg": 15.9
    },
    {
      "date": "Jan 18",
      "date_full": "2026-01-18",
      "count": 13,
      "moving_avg": 15.6
    },
    {
      "date": "Jan 19",
      "date_full": "2026-01-19",
      "count": 24,
      "moving_avg": 16.1
    },
    {
      "date": "Jan 20",
      "date_full": "2026-01-20",
      "count": 41,
      "moving_avg": 17.3
    },
    {
      "date": "Jan 21",
      "date_full": "2026-01-21",
      "count": 31,
      "moving_avg": 17.8
    },
    {
      "date": "Jan 22",
      "date_full": "2026-01-22",
      "count": 39,
      "moving_avg": 18.4
    },
    {
      "date": "Jan 23",
      "date_full": "2026-01-23",
      "count": 30,
      "moving_avg": 19.1
    },
    {
      "date": "Jan 24",
      "date_full": "2026-01-24",
      "count": 9,
      "moving_avg": 19.3
    },
    {
      "date": "Jan 25",
      "date_full": "2026-01-25",
      "count": 16,
      "moving_avg": 19.7
    },
    {
      "date": "Jan 26",
      "date_full": "2026-01-26",
      "count": 32,
      "moving_avg": 20.5
    },
    {
      "date": "Jan 27",
      "date_full": "2026-01-27",
      "count": 43,
      "moving_avg": 21.6
    }
  ],
  "moving_avg_30d": [
    14.8,
    15.0,
    14.9,
    14.9,
    14.6,
    14.4,
    15.0,
    15.7,
    15.7,
    15.8,
    15.8,
    15.7,
    15.4,
    14.8,
    15.4,
    16.1,
    16.4,
    16.4,
    16.3,
    15.9,
    15.6,
    16.1,
    17.3,
    17.8,
    18.4,
    19.1,
    19.3,
    19.7,
    20.5,
    21.6
  ],
  "data_quality": {
    "total_records": 744,
    "matched_records": "175",
    "singularity_only": "425",
    "parcl_only": "144",
    "pnl_coverage": 37.2,
    "details_coverage": 80.6
  },
  "top_markets": [
    {
      "city": "Phoenix",
      "listings": 21,
      "avg_price": 439190
    },
    {
      "city": "Charlotte",
      "listings": 18,
      "avg_price": 341722
    },
    {
      "city": "Tucson",
      "listings": 18,
      "avg_price": 292500
    },
    {
      "city": "Indianapolis",
      "listings": 13,
      "avg_price": 271000
    },
    {
      "city": "Raleigh",
      "listings": 13,
      "avg_price": 444385
    },
    {
      "city": "Columbia",
      "listings": 12,
      "avg_price": 289333
    },
    {
      "city": "Houston",
      "listings": 12,
      "avg_price": 331667
    },
    {
      "city": "San Antonio",
      "listings": 12,
      "avg_price": 294500
    },
    {
      "city": "Atlanta",
      "listings": 10,
      "avg_price": 286700
    },
    {
      "city": "Colorado Springs",
      "listings": 10,
      "avg_price": 405800
    }
  ],
  "market_concentration": {
    "top5_pct": 7.6,
    "total_markets": 477,
    "total_listings": 1093
  },
  "top_cities": {
    "Indianapolis": 11,
    "Phoenix": 11,
    "Kansas City": 10,
    "Charlotte": 9,
    "Columbia": 9,
    "Tucson": 8,
    "Jacksonville": 8,
    "Las Vegas": 7,
    "Albuquerque": 7,
    "Atlanta": 7,
    "Cincinnati": 6,
    "Houston": 6,
    "Raleigh": 5,
    "Colorado Springs": 5,
    "Dallas": 5
  },
  "cohorts": {
    "new": {
      "count": 70,
      "win_rate": 98.5,
      "avg_profit": 44399,
      "total_realized": 2930314
    },
    "mid": {
      "count": 104,
      "win_rate": 94.6,
      "avg_profit": 41277,
      "total_realized": 3838743
    },
    "old": {
      "count": 100,
      "win_rate": 63.9,
      "avg_profit": 26154,
      "total_realized": 2170800
    },
    "toxic": {
      "count": 43,
      "win_rate": 37.1,
      "avg_profit": -15386,
      "total_realized": -538500
    }
  },
  "this_week": {
    "sales": 200,
    "revenue": 80610000.0,
    "daily_avg": 28.6
  },
  "last_week": {
    "sales": 165,
    "revenue": 60879999.99999999,
    "daily_avg": 23.6
  },
  "wow_change": {
    "sales_pct": 21.2,
    "revenue_pct": 32.4
  },
  "guidance": {
    "q1_target": 1000000000,
    "current_revenue": 288469700.0,
    "days_elapsed": 27,
    "days_remaining": 63,
    "daily_target": 11111111,
    "daily_actual": 10684063,
    "projected_revenue": 961565667,
    "pacing_pct": 96.2,
    "on_track": true
  },
  "ai_insights": {
    "velocity_insight": "Sales accelerated 21.2% week-over-week to 200 homes, strongest momentum yet.",
    "guidance_insight": "Revenue tracking 96.2% to Q1 target with 63 days remaining.",
    "pattern_insight": "79.1% win rate generating $46K average profit per successful transaction.",
    "generated_at": "2026-01-28T10:01:56.595799"
  }
}